fabricatio_tool-0.8.3.dist-info/METADATA
fabricatio_tool-0.8.3.dist-info/WHEEL
fabricatio_tool-0.8.3.dist-info/licenses/LICENSE
fabricatio_tool/__init__.py
fabricatio_tool/actions/__init__.py
fabricatio_tool/capabilities/__init__.py
fabricatio_tool/capabilities/handle.py
fabricatio_tool/capabilities/handle_task.py
fabricatio_tool/capabilities/use_tool.py
fabricatio_tool/config.py
fabricatio_tool/decorators.py
fabricatio_tool/fs/__init__.py
fabricatio_tool/fs/curd.py
fabricatio_tool/fs/readers.py
fabricatio_tool/mcp.py
fabricatio_tool/models/__init__.py
fabricatio_tool/models/collector.py
fabricatio_tool/models/executor.py
fabricatio_tool/models/tool.py
fabricatio_tool/py.typed
fabricatio_tool/rust.cpython-314-darwin.so
fabricatio_tool/rust.pyi
fabricatio_tool/toolboxes/__init__.py
fabricatio_tool/toolboxes/fs.py
fabricatio_tool/workflows/__init__.py
fabricatio_tool-0.8.3.dist-info/RECORD
