Metadata-Version: 2.4
Name: fabricatio-tool
Version: 0.8.3
Classifier: License :: OSI Approved :: MIT License
Classifier: Programming Language :: Python :: 3.12
Classifier: Programming Language :: Python :: 3.13
Classifier: Programming Language :: Python :: 3.14
Classifier: Programming Language :: Python :: Implementation :: CPython
Classifier: Framework :: AsyncIO
Classifier: Framework :: Pydantic :: 2
Classifier: Typing :: Typed
Requires-Dist: fabricatio-core
Requires-Dist: pydantic>=2.11.7
Requires-Dist: questionary>=2.1.0
License-File: LICENSE
Summary: An extension of fabricatio, which brings up the capability to use tool with native python.
Author-email: Whth <zettainspector@foxmail.com>
Requires-Python: >=3.12, <3.15
Project-URL: Homepage, https://github.com/Whth/fabricatio
Project-URL: Repository, https://github.com/Whth/fabricatio
Project-URL: Issues, https://github.com/Whth/fabricatio/issues
